kgraph/nn.py
kgraph/log.py
kgraph/__init__.py
kgraph/loss/SoftplusLoss.py
kgraph/loss/Loss.py
kgraph/loss/MarginLoss.py
kgraph/loss/SigmoidLoss.py
kgraph/loss/__init__.py
kgraph/utils/read.cpython-310-x86_64-linux-gnu.so
kgraph/utils/sample.cpython-310-x86_64-linux-gnu.so
kgraph/utils/read.pxd
kgraph/utils/memory.pxd
kgraph/utils/tools.pyx
kgraph/utils/memory.cpython-310-x86_64-linux-gnu.so
kgraph/utils/evaluation.pyx
kgraph/utils/corrupt.pxd
kgraph/utils/memory.pyx
kgraph/utils/tools.cpython-310-x86_64-linux-gnu.so
kgraph/utils/classification.pyx
kgraph/utils/sample.pyx
kgraph/utils/corrupt.pyx
kgraph/utils/corrupt.cpython-310-x86_64-linux-gnu.so
kgraph/utils/evaluation.cpython-310-x86_64-linux-gnu.so
kgraph/utils/setup.py
kgraph/utils/read.pyx
kgraph/utils/__init__.py
kgraph/utils/classification.cpython-310-x86_64-linux-gnu.so
kgraph-1.1.0.dist-info/METADATA
kgraph-1.1.0.dist-info/WHEEL
kgraph-1.1.0.dist-info/top_level.txt
kgraph-1.1.0.dist-info/LICENSE
kgraph-1.1.0.dist-info/RECORD
