Metadata-Version: 2.1
Name: kgraph
Version: 1.1.0
Summary: A Python library for relational learning on knowledge graphs.
Author: Shuanglong Yao
Author-email: shuanglongyao@gmail.com
License: Apache 2.0
Project-URL: Source, https://github.com/YaoShuang-long/kgraph
Classifier: Operating System :: OS Independent
Classifier: Intended Audience :: Developers
Classifier: Programming Language :: Cython
Classifier: Programming Language :: Python :: 3.7
Classifier: Topic :: Software Development :: Libraries
Requires-Python: >=3.7
License-File: LICENSE
